[
    {
        "total_ram": 16275516,
        "free_ram": 8725556,
        "usage_ram": 7549960,
        "timestamp": "2024-09-09 17:13:02"
    },
    {
        "total_ram": 16275516,
        "free_ram": 8640944,
        "usage_ram": 7634572,
        "timestamp": "2024-09-09 17:13:13"
    },
    {
        "total_ram": 16275516,
        "free_ram": 8752696,
        "usage_ram": 7522820,
        "timestamp": "2024-09-09 17:13:24"
    },
    {
        "total_ram": 16275516,
        "free_ram": 8736424,
        "usage_ram": 7539092,
        "timestamp": "2024-09-09 17:13:34"
    },
    {
        "total_ram": 16275516,
        "free_ram": 8743936,
        "usage_ram": 7531580,
        "timestamp": "2024-09-09 17:13:44"
    },
    {
        "total_ram": 16275516,
        "free_ram": 8728460,
        "usage_ram": 7547056,
        "timestamp": "2024-09-09 17:13:54"
    },
    {
        "total_ram": 16275516,
        "free_ram": 8195412,
        "usage_ram": 8080104,
        "timestamp": "2024-09-09 17:14:04"
    },
    {
        "total_ram": 16275516,
        "free_ram": 8617916,
        "usage_ram": 7657600,
        "timestamp": "2024-09-09 17:14:16"
    },
    {
        "total_ram": 16275516,
        "free_ram": 8680300,
        "usage_ram": 7595216,
        "timestamp": "2024-09-09 17:14:26"
    },
    {
        "total_ram": 16275516,
        "free_ram": 8636976,
        "usage_ram": 7638540,
        "timestamp": "2024-09-09 17:14:36"
    },
    {
        "total_ram": 16275516,
        "free_ram": 8607480,
        "usage_ram": 7668036,
        "timestamp": "2024-09-09 17:14:46"
    },
    {
        "total_ram": 16275516,
        "free_ram": 8643756,
        "usage_ram": 7631760,
        "timestamp": "2024-09-09 17:14:56"
    },
    {
        "total_ram": 16275516,
        "free_ram": 8282900,
        "usage_ram": 7992616,
        "timestamp": "2024-09-09 17:15:06"
    },
    {
        "total_ram": 16275516,
        "free_ram": 8630600,
        "usage_ram": 7644916,
        "timestamp": "2024-09-09 17:15:18"
    }
]